herhoopstats/__init__.py
herhoopstats/api.py
herhoopstats/structs.py
herhoopstats-0.0.1.dist-info/LICENSE
herhoopstats-0.0.1.dist-info/METADATA
herhoopstats-0.0.1.dist-info/WHEEL
herhoopstats-0.0.1.dist-info/top_level.txt
herhoopstats-0.0.1.dist-info/RECORD
